<?xml version="1.0" encoding="windows-1251"?>
<questestinterop><item ident="QUE40"><presentation><material><mattext>Действия по настройке мыши, доступные на странице настроек интерфейса, подразумевают:</mattext></material><response_lid ident="LID40" rcardinality="Multiple"><render_choice><response_label ident="ANS967"><material><mattext>изменение поведения кнопок мыши на страницах с формами отчетов</mattext></material></response_label><response_label ident="ANS968"><material><mattext>изменение поведения кнопок мыши на страницах с формами редактирования</mattext></material></response_label><response_label ident="ANS969"><material><mattext>выбор изображений для указателей мыши</mattext></material></response_label></render_choice></response_lid></presentation><resprocessing><respcondition><conditionvar><varequal respident="LID40">ANS967</varequal></conditionvar><setvar>10</setvar></respcondition></resprocessing><bitrix><description></description><description_type>text</description_type><self>N</self><sort>500</sort><active>Y</active></bitrix></item></questestinterop>